repo_helper/blocks/__init__.py
repo_helper/blocks/docs_installation_block_template.rst
repo_helper/blocks/docs_links_block_template.rst
repo_helper/blocks/docs_shields_block_template.rst
repo_helper/blocks/readme_installation_block_no_pypi_template.rst
repo_helper/blocks/readme_installation_block_template.rst
repo_helper/cli/commands/__init__.py
repo_helper/cli/commands/add.py
repo_helper/cli/commands/broomstick.py
repo_helper/cli/commands/conda_recipe.py
repo_helper/cli/commands/init.py
repo_helper/cli/commands/make_schema.py
repo_helper/cli/commands/release.py
repo_helper/cli/commands/show.py
repo_helper/cli/commands/suggest.py
repo_helper/cli/commands/wizard.py
repo_helper/cli/__init__.py
repo_helper/cli/utils.py
repo_helper/configuration/__init__.py
repo_helper/configuration/conda_anaconda.py
repo_helper/configuration/documentation.py
repo_helper/configuration/metadata.py
repo_helper/configuration/optional_features.py
repo_helper/configuration/other.py
repo_helper/configuration/packaging.py
repo_helper/configuration/python_versions_.py
repo_helper/configuration/testing.py
repo_helper/configuration/travis.py
repo_helper/configuration/utils.py
repo_helper/files/__init__.py
repo_helper/files/bots.py
repo_helper/files/ci_cd.py
repo_helper/files/contributing.py
repo_helper/files/docs.py
repo_helper/files/gitignore.py
repo_helper/files/isort.cfg
repo_helper/files/linting.py
repo_helper/files/old.py
repo_helper/files/packaging.py
repo_helper/files/pre_commit.py
repo_helper/files/readme.py
repo_helper/files/testing.py
repo_helper/init_repo_files/README.rst
repo_helper/init_repo_files/__init__._py
repo_helper/init_repo_files/bsd2._py
repo_helper/init_repo_files/bsd3._py
repo_helper/init_repo_files/generic._py
repo_helper/init_repo_files/git_download.png
repo_helper/init_repo_files/gpl2._py
repo_helper/init_repo_files/gpl2_plus._py
repo_helper/init_repo_files/gpl3._py
repo_helper/init_repo_files/gpl3_plus._py
repo_helper/init_repo_files/index.rst
repo_helper-2025.6.3.dist-info/LICENSE
repo_helper-2025.6.3.dist-info/METADATA
repo_helper-2025.6.3.dist-info/WHEEL
repo_helper-2025.6.3.dist-info/entry_points.txt
repo_helper-2025.6.3.dist-info/RECORD
