Metadata-Version: 2.2
Name: repo-helper
Version: 2025.6.3
Summary: A tool to manage configuration files, build scripts etc. across multiple projects.
Author-email: Dominic Davis-Foster <dominic@davis-foster.co.uk>
License: LGPL-3.0-or-later
Keywords: configuration
Home-page: https://github.com/repo-helper/repo_helper
Project-URL: Issue Tracker, https://github.com/repo-helper/repo_helper/issues
Project-URL: Source Code, https://github.com/repo-helper/repo_helper
Project-URL: Documentation, https://docs.repo-helper.uk
Platform: Windows
Platform: macOS
Platform: Linux
Classifier: Development Status :: 4 - Beta
Classifier: Environment :: Console
Classifier: Intended Audience :: Developers
Classifier: License :: OSI Approved :: GNU Lesser General Public License v3 or later (LGPLv3+)
Classifier: Operating System :: OS Independent
Classifier: Programming Language :: Python
Classifier: Programming Language :: Python :: 3 :: Only
Classifier: Programming Language :: Python :: 3.7
Classifier: Programming Language :: Python :: 3.8
Classifier: Programming Language :: Python :: 3.9
Classifier: Programming Language :: Python :: 3.10
Classifier: Programming Language :: Python :: 3.11
Classifier: Programming Language :: Python :: 3.12
Classifier: Programming Language :: Python :: 3.13
Classifier: Programming Language :: Python :: Implementation :: CPython
Classifier: Programming Language :: Python :: Implementation :: PyPy
Classifier: Topic :: Software Development :: Version Control :: Git
Classifier: Topic :: Utilities
Classifier: Typing :: Typed
Requires-Python: >=3.7
Requires-Dist: apeye>=1.0.0
Requires-Dist: attrs>=20.3.0
Requires-Dist: click==7.1.2
Requires-Dist: configconfig>=0.5.0
Requires-Dist: consolekit>=1.2.2
Requires-Dist: dict2css>=0.2.0
Requires-Dist: dom-toml>=2.0.0
Requires-Dist: domdf-python-tools>=3.2.0
Requires-Dist: dulwich>=0.20.5
Requires-Dist: first>=2.0.2
Requires-Dist: isort>=5.5.2
Requires-Dist: jinja2>=2.11.3
Requires-Dist: mkrecipe>=0.3.0
Requires-Dist: natsort>=7.1.1
Requires-Dist: packaging>=20.9
Requires-Dist: pypi-json>=0.2.1
Requires-Dist: pyproject-parser>=0.11.0
Requires-Dist: ruamel.yaml>=0.17.4
Requires-Dist: shippinglabel>=1.7.1
Requires-Dist: shippinglabel-conda>=0.1.0
Requires-Dist: southwark>=0.7.1
Requires-Dist: tabulate>=0.8.8
Requires-Dist: typing-extensions>=3.7.4.3
Requires-Dist: whey>=0.0.17
Requires-Dist: yapf-isort>=0.5.2
Requires-Dist: check-wheel-contents>=0.2.0; extra == 'testing'
Requires-Dist: coincidence>=0.2.0; extra == 'testing'
Requires-Dist: pytest>=6.2.0; extra == 'testing'
Requires-Dist: dulwich<=0.20.33,>=0.20.5; extra == 'cli'
Requires-Dist: check-wheel-contents>=0.2.0; extra == 'all'
Requires-Dist: coincidence>=0.2.0; extra == 'all'
Requires-Dist: dulwich<=0.20.33,>=0.20.5; extra == 'all'
Requires-Dist: pytest>=6.2.0; extra == 'all'
Provides-Extra: testing
Provides-Extra: cli
Provides-Extra: all
